{
	"animations": [
		{
			"loop": false,
			"offsets": [
				61,
				203
			],
			"anim": "idle",
			"fps": 24,
			"name": "idle",
			"indices": []
		},
		{
			"loop": false,
			"offsets": [
				61,
				203
			],
			"anim": "singDOWN",
			"fps": 24,
			"name": "down",
			"indices": []
		},
		{
			"loop": false,
			"offsets": [
				62,
				203
			],
			"anim": "singUP",
			"fps": 24,
			"name": "up",
			"indices": []
		},
		{
			"loop": false,
			"offsets": [
				62,
				203
			],
			"anim": "singRIGHT",
			"fps": 24,
			"name": "right",
			"indices": []
		},
		{
			"loop": false,
			"offsets": [
				62,
				203
			],
			"anim": "singLEFT",
			"fps": 24,
			"name": "left",
			"indices": []
		}
	],
	"vocals_file": "",
	"no_antialiasing": false,
	"image": "characters/GREENkopey",
	"position": [
		-80,
		-40
	],
	"healthicon": "icon-GREEN",
	"flip_x": false,
	"healthbar_colors": [
		75,
		207,
		85
	],
	"camera_position": [
		60,
		-250
	],
	"sing_duration": 4,
	"scale": 0.9,
	"_editor_isPlayer": false
}
